{
  "id": "stabilize-goal-flow",
  "title": "Stabilize goal-flow refactor",
  "description": "Convert tick.sh into a TypeScript preflight chain on the engine's existing architecture. Each task issue extracts one piece of tick.sh into a named TS script with unit tests. Final cutover deletes tick.sh. Dogfooded on this fork; upstreamed to aharonyaircohen/kody-engine via cross-repo PR when complete.",
  "state": "active",
  "createdAt": "2026-05-10T12:12:16Z",
  "updatedAt": "2026-05-20T14:04:26.917979Z",
  "goalIssueNumber": 1,
  "lastDispatchedIssue": 2
}
